brackets/__init__.py
brackets/exceptions.py
brackets/py.typed
brackets/mixins/__init__.py
brackets/mixins/__init__.pyi
brackets/mixins/access.py
brackets/mixins/access.pyi
brackets/mixins/form_views.py
brackets/mixins/form_views.pyi
brackets/mixins/forms.py
brackets/mixins/forms.pyi
brackets/mixins/http.py
brackets/mixins/http.pyi
brackets/mixins/queries.py
brackets/mixins/queries.pyi
brackets/mixins/redirects.py
brackets/mixins/redirects.pyi
brackets/mixins/rest_framework.py
brackets/mixins/rest_framework.pyi
django_brackets-2024.dist-info/LICENSE.txt
django_brackets-2024.dist-info/WHEEL
django_brackets-2024.dist-info/METADATA
django_brackets-2024.dist-info/RECORD
