Metadata-Version: 2.1
Name: django-brackets
Version: 2024
Summary: Mixins to make class-based generic views simpler and neater.
Author: klove
Requires-Python: >=3.10
Classifier: Development Status :: 4 - Beta
Classifier: Environment :: Web Environment
Classifier: Framework :: Django :: 4.2
Classifier: Framework :: Django
Classifier: Intended Audience :: Developers
Classifier: License :: OSI Approved :: Apache Software License
Classifier: Natural Language :: English
Classifier: Programming Language :: Python :: 3 :: Only
Classifier: Programming Language :: Python :: 3.11
Classifier: Programming Language :: Python
Classifier: Topic :: Software Development :: Libraries :: Python Modules
Requires-Dist: django-rest-framework>=0.1.0
Requires-Dist: django<6,>=4.2
Requires-Dist: flit<4,>=3.2
Requires-Dist: django-stubs[compatible-mypy] ; extra == "development"
Requires-Dist: djangorestframework-stubs[compatible-mypy] ; extra == "development"
Requires-Dist: interrogate ; extra == "development"
Requires-Dist: mypy ; extra == "development"
Requires-Dist: ruff ; extra == "development"
Requires-Dist: mkdocs-material>=9.1.16 ; extra == "documentation"
Requires-Dist: mkdocs>=1.4.3 ; extra == "documentation"
Requires-Dist: pygments>=2.15.1 ; extra == "documentation"
Requires-Dist: pymdown-extensions>=10.0.1 ; extra == "documentation"
Requires-Dist: coverage ; extra == "testing"
Requires-Dist: pytest ; extra == "testing"
Requires-Dist: pytest-cov ; extra == "testing"
Requires-Dist: pytest-django ; extra == "testing"
Requires-Dist: pytest-lazy-fixture ; extra == "testing"
Requires-Dist: pytest-randomly ; extra == "testing"
Requires-Dist: pytest-xdist ; extra == "testing"
Requires-Dist: tox ; extra == "testing"
Project-URL: repository, https://github.com/brack3t/django-brackets/
Provides-Extra: development
Provides-Extra: documentation
Provides-Extra: testing
